abarorm/__init__.py
abarorm/psql.py
abarorm/sqlite.py
abarorm/fields/__init__.py
abarorm/fields/psql.py
abarorm/fields/sqlite.py
abarorm-5.5.2.dist-info/LICENSE
abarorm-5.5.2.dist-info/METADATA
abarorm-5.5.2.dist-info/WHEEL
abarorm-5.5.2.dist-info/top_level.txt
abarorm-5.5.2.dist-info/RECORD
