Metadata-Version: 2.1
Name: abarorm
Version: 5.5.2
Summary: abarorm is a lightweight and easy-to-use Object-Relational Mapping (ORM) library for SQLite and PostgreSQL databases in Python. It aims to provide a simple and intuitive interface for managing database models and interactions.
Home-page: https://github.com/prodbygodfather/abarorm
Author: Mahdi Ghasemi
Author-email: prodbygodfather@gmail.com
License: Apache License
Keywords: orm database sqlite postgresql mysql lightweight python
Classifier: Development Status :: 3 - Alpha
Classifier: Intended Audience :: Developers
Classifier: License :: OSI Approved :: MIT License
Classifier: Programming Language :: Python :: 3.8
Classifier: Programming Language :: Python :: 3.9
Classifier: Programming Language :: Python :: 3.10
Classifier: Programming Language :: Python :: 3.11
Classifier: Programming Language :: Python :: 3.12
Classifier: Programming Language :: Python :: 3.13
Classifier: Programming Language :: Python :: 3.14
Classifier: Topic :: Database
Classifier: Topic :: Software Development :: Libraries :: Python Modules
Classifier: Operating System :: OS Independent
Requires-Python: >=3.8
License-File: LICENSE
Requires-Dist: psycopg2-binary >=2.9.0
Provides-Extra: postgresql
Requires-Dist: psycopg2-binary >=2.9.0 ; extra == 'postgresql'
